LICENSE.txt
README.md
pyproject.toml
src/MT_PY_WebNotificationPush.egg-info/PKG-INFO
src/MT_PY_WebNotificationPush.egg-info/SOURCES.txt
src/MT_PY_WebNotificationPush.egg-info/dependency_links.txt
src/MT_PY_WebNotificationPush.egg-info/top_level.txt
src/MT_PY_WebPushNotification/manage.py
src/MT_PY_WebPushNotification/MT_PY_WebPushNotification/__init__.py
src/MT_PY_WebPushNotification/MT_PY_WebPushNotification/asgi.py
src/MT_PY_WebPushNotification/MT_PY_WebPushNotification/settings.py
src/MT_PY_WebPushNotification/MT_PY_WebPushNotification/urls.py
src/MT_PY_WebPushNotification/MT_PY_WebPushNotification/views.py
src/MT_PY_WebPushNotification/MT_PY_WebPushNotification/wsgi.py
src/virenv/Lib/site-packages/six.py
src/virenv/Lib/site-packages/typing_extensions.py
src/virenv/Lib/site-packages/_distutils_hack/__init__.py
src/virenv/Lib/site-packages/_distutils_hack/override.py
src/virenv/Lib/site-packages/asgiref/__init__.py
src/virenv/Lib/site-packages/asgiref/compatibility.py
src/virenv/Lib/site-packages/asgiref/current_thread_executor.py
src/virenv/Lib/site-packages/asgiref/local.py
src/virenv/Lib/site-packages/asgiref/server.py
src/virenv/Lib/site-packages/asgiref/sync.py
src/virenv/Lib/site-packages/asgiref/testing.py
src/virenv/Lib/site-packages/asgiref/timeout.py
src/virenv/Lib/site-packages/asgiref/typing.py
src/virenv/Lib/site-packages/asgiref/wsgi.py
src/virenv/Lib/site-packages/certifi/__init__.py
src/virenv/Lib/site-packages/certifi/__main__.py
src/virenv/Lib/site-packages/certifi/core.py
src/virenv/Lib/site-packages/cffi/__init__.py
src/virenv/Lib/site-packages/cffi/api.py
src/virenv/Lib/site-packages/cffi/backend_ctypes.py
src/virenv/Lib/site-packages/cffi/cffi_opcode.py
src/virenv/Lib/site-packages/cffi/commontypes.py
src/virenv/Lib/site-packages/cffi/cparser.py
src/virenv/Lib/site-packages/cffi/error.py
src/virenv/Lib/site-packages/cffi/ffiplatform.py
src/virenv/Lib/site-packages/cffi/lock.py
src/virenv/Lib/site-packages/cffi/model.py
src/virenv/Lib/site-packages/cffi/pkgconfig.py
src/virenv/Lib/site-packages/cffi/recompiler.py
src/virenv/Lib/site-packages/cffi/setuptools_ext.py
src/virenv/Lib/site-packages/cffi/vengine_cpy.py
